pykunai/__init__.py
pykunai/event.py
pykunai/graph.py
pykunai/py.typed
pykunai/utils.py
pykunai/misp/export.py
pykunai/tools/iocgen.py
pykunai/tools/kunai_graph.py
pykunai/tools/kunai_stats.py
pykunai/tools/kunai_to_misp.py
pykunai/tools/misp_to_kunai.py
pykunai/tools/search.py
pykunai/tools/config/config.example.toml
pykunai-0.1.10.dist-info/METADATA
pykunai-0.1.10.dist-info/WHEEL
pykunai-0.1.10.dist-info/entry_points.txt
pykunai-0.1.10.dist-info/licenses/LICENSE
pykunai-0.1.10.dist-info/RECORD
