Metadata-Version: 2.4
Name: pykunai
Version: 0.1.10
Summary: Python library and tools to work with Kunai
Author-email: qjerome <quentin.jerome@circl.lu>
License-File: LICENSE
Requires-Python: >=3.7
Requires-Dist: graphviz
Requires-Dist: pymisp
Requires-Dist: toml
